ez_video_convert/__init__.py
ez_video_convert/mov2mp4.py
ez_video_convert-0.1.dist-info/METADATA
ez_video_convert-0.1.dist-info/WHEEL
ez_video_convert-0.1.dist-info/entry_points.txt
ez_video_convert-0.1.dist-info/top_level.txt
ez_video_convert-0.1.dist-info/RECORD
