Metadata-Version: 2.1
Name: ez-video-convert
Version: 0.1
Summary: A simple tool to convert .mov video files to .mp4 format.
Home-page: https://github.com/yourusername/ez-video-convert
Author: Malek Ibrahim
Author-email: shmeek8@gmail.com
Classifier: Programming Language :: Python :: 3
Classifier: License :: OSI Approved :: MIT License
Classifier: Operating System :: OS Independent
Requires-Dist: click
Requires-Dist: pyperclip
